LICENSE
MANIFEST.in
README.md
pyproject.toml
setup.py
AddNoise/AddNoise.cpp
AddNoise/AddNoise.h
AddNoise/AddNoise_AVX2.cpp
AddNoise/AddNoise_AVX512.cpp
AddNoise/AddNoise_SSE2.cpp
AddNoise/pcg.h
AddNoise/perlin.cpp
AddNoise/perlin.h
AddNoise/poisson.h
AddNoise/simplex.cpp
AddNoise/simplex.h
AddNoise/VCL2/instrset.h
AddNoise/VCL2/instrset_detect.cpp
AddNoise/VCL2/vector_convert.h
AddNoise/VCL2/vectorclass.h
AddNoise/VCL2/vectorf128.h
AddNoise/VCL2/vectorf256.h
AddNoise/VCL2/vectorf256e.h
AddNoise/VCL2/vectorf512.h
AddNoise/VCL2/vectorf512e.h
AddNoise/VCL2/vectori128.h
AddNoise/VCL2/vectori256.h
AddNoise/VCL2/vectori256e.h
AddNoise/VCL2/vectori512.h
AddNoise/VCL2/vectori512e.h
AddNoise/VCL2/vectori512s.h
AddNoise/VCL2/vectori512se.h
AddNoise/VCL2/vectormath_common.h
AddNoise/VCL2/vectormath_exp.h
AddNoise/VCL2/vectormath_hyp.h
AddNoise/VCL2/vectormath_lib.h
AddNoise/VCL2/vectormath_trig.h
vsnoise/__init__.py
vsnoise.egg-info/PKG-INFO
vsnoise.egg-info/SOURCES.txt
vsnoise.egg-info/dependency_links.txt
vsnoise.egg-info/entry_points.txt
vsnoise.egg-info/requires.txt
vsnoise.egg-info/top_level.txt