Metadata-Version: 2.4
Name: vsnoise
Version: 1
License-File: LICENSE
Requires-Dist: vsauto
Dynamic: license-file
